{"name": "Hank, ja i Joe", "link": "https://www.kaczmarski.art.pl/tworczosc/wiersze/hank-ja-i-joe/", "year": "1974", "text": "(wg J. Casha)\n\u015amier\u0107 kryje w sobie pustyni g\u0142\u0105b,\nW dzie\u0144 jest tu upa\u0142, a w nocy zi\u0105b,\nLecz z\u0142oto to z\u0142oto, wi\u0119c mimo to\nDoszli\u015bmy tu: Hank, ja, i Joe.\nDoszli\u015bmy z trudem, lecz ten trud\nPrzyni\u00f3s\u0142 nam tylko g\u0142\u00f3d i ch\u0142\u00f3d,\nA gdy ju\u017c i\u015b\u0107 nie mog\u0142em \u2013 wody brak \u2013\nHank m\u00f3wi Joemu tak\nOn ginie z pragnienia\nJego j\u0119k nic nie zmienia,\nPo\u0142\u00f3\u017cmy go lepiej tu, w ten piach,\nOn nie ma ju\u017c nawet si\u0142 na strach,\nTu ko\u0144czy si\u0119 jego \u017cycia tre\u015b\u0107,\nJoe, chod\u017amy st\u0105d, nie mog\u0119 jego j\u0119ku znie\u015b\u0107.\nHank nie m\u00f3g\u0142 ju\u017c mojego j\u0119ku znie\u015b\u0107\nGdym ockn\u0105\u0142 si\u0119, s\u0142o\u0144ce zachodzi\u0142o ju\u017c,\nOpad\u0142 na ziemie pustynny kurz,\nS\u0119py kr\u0105\u017cy\u0142y niedaleko mnie\u2026\nZ Hankiem i Joem pewnie te\u017c jest \u017ale.\nWtem co\u015b mnie tkn\u0119\u0142o unios\u0142em si\u0119\u2026\nUjrza\u0142em bry\u0142y z\u0142ota wok\u00f3\u0142 mnie.\nTo z\u0142oto rozsiane u mych st\u00f3p\nOzdobi wkr\u00f3tce m\u00f3j gr\u00f3b.\nBo gin\u0119 z pragnienia\nM\u00f3j j\u0119k nic nie zmienia,\nPo\u0142o\u017cyli go tutaj, w ten piach i kurz,\nA Hank powiedzia\u0142, \u017ce to koniec ju\u017c\nTu mi si\u0119 ko\u0144czy \u017cycia tre\u015b\u0107,\n\u017be ju\u017c nie mo\u017ce mego j\u0119ku znie\u015b\u0107.\nHank nie m\u00f3g\u0142 ju\u017c mojego j\u0119ku znie\u015b\u0107.\n", "special_attrs": {}, "id": "168", "special": false}