{"name": "O zachowaniu przy stole", "link": "https://www.kaczmarski.art.pl/tworczosc/wiersze/o-zachowaniu-przy-stole/", "year": "24.10.1993", "text": "(za J. Kitowiczem)\nPolski st\u00f3\u0142 zastawiony. Na chor\u0105gwi obrusach\nPotu, patoki, posoki \u2013 tysi\u0105cletni l\u015bni haft.\n\u015aniada\u0142 na nim kr\u00f3l, kanclerz, ksi\u0105dz, parobek i husarz,\nNici Turczyn dostarczy\u0142, Niemiec doda\u0142 warsztat i kraft.\nLitwin podszy\u0142 uporem Lach\u00f3w niefrasobliwo\u015b\u0107\nDzik\u0105 serca t\u0119sknot\u0119 Kozak wni\u00f3s\u0142, smutek \u2013 \u017byd;\nW\u0142och \u0142aci\u0144skie sentencje wpl\u00f3t\u0142 w tkanin\u0119 cierpliw\u0105,\nEstetyczny z cyrylic\u0105 wywo\u0142uj\u0105c tym zgrzyt.\nPenelopa narod\u00f3w \u2013 co utka\u0142a to pru\u0142a,\nZalotnik\u00f3w zach\u0142anno\u015b\u0107 dope\u0142ni\u0142a jej los;\nZanim prac\u0119 podj\u0119\u0142a Dejanira nieczu\u0142a\nSzyj\u0105c giez\u0142a \u015bmiertelne rzeszom Herkules\u00f3w \u2013 na stos.\nNa \u017ca\u0142obno-rubasznym wi\u0119c ucztujem brokacie,\nGdy ze s\u0142omy zza cholew dobywamy swych \u0142ych!\nMo\u017ce nie tak jak drzewiej, nie obficiej, bogaciej\nLecz \u2013 na swoim si\u0119gamy do kielich\u00f3w i mich!\nWielki budz\u0105 apetyt \u015bwie\u017cego pa\u0144stwa pasztety,\nKrzepki kordia\u0142 szaleju ciska iskr\u0119 w dusz chrust!\nRozgryzamy na miazg\u0119 krwawych kiszek konkrety\nA na wety \u2013 ko\u015bcio\u0142a ko\u0142acz podnosimy do ust.\nNa subtelne bebechy zbyt tre\u015bciwa to strawa,\nW \u0142by, gdzie m\u00f3zg si\u0119 przelewa \u2013 nie nalejesz po brzeg!\nTorsy w torsjach trzepocz\u0105 na z\u0142ocistych zastawach,\nZ rybich warg \u2013 farszu kartacz, w zadach z hukiem pruje si\u0119 \u015bcieg!\nBra\u0107mi wzgardzi, kto z gard\u0142a pu\u015bci sok na uboczu:\nNie odzyska pozycji w towarzystwie ich mord;\nZajm\u0105 wnet jego miejsce, gdy si\u0119 tylko z krzes\u0142a wytoczy\nPo\u017c\u0105dliwe \u017co\u0142\u0105dki z chrapk\u0105 na wy\u017cerk\u0119 na borg.\nNieudana to uczta co si\u0119 ko\u0144czy przytomnie,\nJe\u015bli go\u015bcie w otch\u0142ann\u0105 nie zapadn\u0105 si\u0119 g\u0142\u0105b,\nKiedy jeden za drugim zdo\u0142a sobie przypomnie\u0107\nKomu nak\u0142ad\u0142 po pysku, kto mu z\u0142ama\u0142 nos, wybi\u0142 z\u0105b.\nZatem jedzmy i pijmy, korzystajmy z okazji\nBo B\u00f3g wie kiedy znowu sam nakryje si\u0119 st\u00f3\u0142!\nB\u0119d\u0105 o nas pami\u0119ta\u0107 w Europie i w Azji\nJak si\u0119 biesi docze\u015bnie, kto histori\u0105 si\u0119 stru\u0142!\nEuropa i Azja! Miazmat\u00f3w ma\u0142mazja!\nKaruzela i rze\u017ania! Paysage id\u00e9al!\nHipokryzja finezji! Na amnezj\u0119 \u2013 fantazja!\nDzie\u0144 za dniem zmartwychwstanie \u2013 msza, pokuta \u2013 i bal!\n", "special_attrs": {}, "id": "363", "special": false}