{"name": "Wszystko, co mi si\u0119 zdarzy\u2026", "link": "https://www.kaczmarski.art.pl/tworczosc/wiersze/wszystko-co-mi-sie-zdarzy/", "year": "1995", "text": "Wszystko, co mi si\u0119 zdarzy,\n\u017b\u0142obi \u015blad w mojej twarzy \u2013\nA mnie si\u0119 przecie\u017c wci\u0105\u017c marzy\nTwarz inna ni\u017c ta, kt\u00f3r\u0105 mam.\nWi\u0119c nie unikam masa\u017cy \u2013\nDaj\u0119 si\u0119 kraja\u0107 i pra\u017cy\u0107,\nBy z twarzy stworzy\u0107 o\u0142tarzyk,\nPrzed kt\u00f3rym ukl\u0105k\u0142bym sam.\nDobry jest ka\u017cdy spos\u00f3b,\nBy si\u0119 odmieni\u0107 ukradkiem \u2013\nJe\u015bli w\u0142asnego losu\nJu\u017c musz\u0119\nKoronnym by\u0107 \u015bwiadkiem.\n", "special_attrs": {}, "id": "650", "special": false}