{"name": "Ballada \u017cebracza", "link": "https://www.kaczmarski.art.pl/tworczosc/wiersze/ballada-zebracza/", "year": "8.9.1989", "text": "Dajcie mi, prosz\u0119, co \u0142aska.\n\u017bebrak \u2013 te\u017c cz\u0142owiek, do diaska!\n\u015apiewa\u0107 ju\u017c nie mam si\u0142y,\n\u017barty mi si\u0119 sko\u0144czy\u0142y.\nSiedz\u0119 na Placu Zamkowym\nZ tym, co na plecach zosta\u0142o,\nSi\u0119gam po rozum do g\u0142owy,\nLecz rozum \u2013 by \u017cy\u0107 \u2013 to za ma\u0142o!\nT\u0142uk\u0105 o pier\u015b resztki serca,\nSerce nadziej\u0105 frymarczy,\nLecz \u2013 mo\u017ce jestem oszczerca \u2013\nSerce \u2013 by \u017cy\u0107 \u2013 nie wystarczy!\nDajcie mi, prosz\u0119, co \u0142aska.\n\u017bebrak \u2013 te\u017c cz\u0142owiek, do diaska!\n\u015apiewa\u0107 ju\u017c nie mam si\u0142y,\n\u017barty mi si\u0119 sko\u0144czy\u0142y.\nM\u00f3wi\u0105 mi \u2013 wsta\u0144 i zapracuj!\nRaz jeszcze zakasz r\u0119kawy\nAlbo zabieraj si\u0119 z placu,\nBo szpecisz pi\u0119kno Warszawy.\nTu zagraniczni tury\u015bci\nWidzie\u0107 chc\u0105 cud odbudowy,\nA ty wra\u017cenia im niszczysz\n\u017bebrz\u0105c na Placu Zamkowym.\nDajcie mi, prosz\u0119, co \u0142aska.\n\u017bebrak \u2013 te\u017c cz\u0142owiek, do diaska!\n\u015apiewa\u0107 ju\u017c nie mam si\u0142y,\n\u017barty mi si\u0119 sko\u0144czy\u0142y.\nGdybym \u0142ez troch\u0119 mia\u0142 jeszcze,\nTobym nad sob\u0105 zap\u0142aka\u0142.\nKto dzi\u015b pami\u0119ta w tym mie\u015bcie,\n\u017be to ja budowa\u0142em Barbakan!\nCz\u0142owiek bez daty urodzin,\nCz\u0142owiek bez dnia swych imienin \u2013\n\u017bycie odda\u0142em urodzie\nRenesansowych kamienic.\nDajcie mi, prosz\u0119, co \u0142aska.\n\u017bebrak \u2013 te\u017c cz\u0142owiek, do diaska!\n\u015apiewa\u0107 ju\u017c nie mam si\u0142y,\n\u017barty mi si\u0119 sko\u0144czy\u0142y.\nNigdy nikomu nie znany,\nPo \u0142okcie w glinie i w piachu\nRy\u0142em, jak kret tresowany\nTunel na Trasie Wsch\u00f3d-Zach\u00f3d.\nI jakby mi by\u0142o za ma\u0142o\nPracy do grobowej deski \u2013\nP\u00f3ki si\u0142 jeszcze starcza\u0142o\nStawia\u0142em Zamek Kr\u00f3lewski.\nWi\u0119c dajcie mi, prosz\u0119, co \u0142aska.\n\u017bebrak \u2013 te\u017c cz\u0142owiek, do diaska!\n\u015apiewa\u0107 ju\u017c nie mam si\u0142y,\n\u017barty mi si\u0119 sko\u0144czy\u0142y.\nNie m\u00f3wcie wi\u0119c, \u017ce co\u015b niszcz\u0119,\nNie m\u00f3wcie mi, \u017ce co\u015b szpec\u0119,\nBo moje r\u0119ce s\u0105 czystsze\nNi\u017c wasze my\u015bli i serca.\nTkwi\u0107 chc\u0119 tu dusz\u0105 i cia\u0142em,\nSpr\u00f3bujcie mi to odebra\u0107!\nTo miasto \u2013 ja zbudowa\u0142em\nBy mie\u0107 na staro\u015b\u0107 \u2013 gdzie \u017cebra\u0107\u2026\nDajcie mi, prosz\u0119, co \u0142aska.\n\u017bebrak \u2013 te\u017c cz\u0142owiek, do diaska!\n\u015apiewa\u0107 ju\u017c nie mam si\u0142y,\nI \u017carty \u2013 si\u0119 sko\u0144czy\u0142y.\n", "special_attrs": {"search": {"wiadomo\u015bci": [{"title": "Ballada \u017cebracza www.kaczmarski.art.pl", "url": "https://www.kaczmarski.art.pl/tworczosc/wiersze/ballada-zebracza/", "desc": " Oct 10, 2017  \u00b7  \u017bebrak \u2013 te\u017c cz\u0142owiek, do diaska! \u015apiewa\u0107 ju\u017c nie mam si\u0142y, \u017barty mi si\u0119 sko\u0144czy\u0142y. M\u00f3wi\u0105 mi \u2013 wsta\u0144 i zapracuj! "}, {"title": "Jacek Kaczmarski - \"Ballada \u017cebracza\" - YouTube", "url": "https://www.youtube.com/watch?v=EODgeIigxlQ", "desc": " Sep 21, 2016  \u00b7  Dajcie mi, prosz\u0119, co \u0142aska. \u017bebrak \u2013 te\u017c cz\u0142owiek, do diaska! \u015apiewa\u0107 ju\u017c nie mam si\u0142y, \u017barty mi si\u0119 sko\u0144czy\u0142y. Siedz\u0119 na Placu Zamkowym Z\u00a0... "}, {"title": "17 Jacek Kaczmarski - Piosenka \u017cebracza (Bankiet 1992) - YouTube", "url": "https://www.youtube.com/watch?v=XEZI88TxLtI", "desc": " Apr 6, 2022  \u00b7  Utw\u00f3r \"Piosenka \u017cebracza\" pochodzi z albumu koncertowego Jacka Kaczmarskiego \"Bankiet\" wydanego w 1992 roku przez Pomaton EMI. "}, {"title": "W\u0105tpliwo\u015bci dot. autorstwa tekstu/muzyki - Jacek Kaczmarski", "url": "http://kaczmarski.art.pl/forum/showthread.php?tid=7920", "desc": " 221 Ballada \u017cebracza \u2013 Jacek Kaczmarski 222 Odnosimy si\u0119\u2026 \u2013 Jacek Kaczmarski 223 Pan Podbipi\u0119ta \u2013 Jacek Kaczmarski 224 Pan Kmicic \u2013 Jacek Kaczmarski 225 Pan\u00a0... "}, {"title": "Ballada \u017cebracza (Jacek Kaczmarski) - Duszan G\u0119dziec - SoundCloud", "url": "https://soundcloud.com/duszan-g-dziec/08-ballada-ebracza-jacek", "desc": " Jun 28, 2017  \u00b7  Amatorska pr\u00f3ba nagrania w\u0142asnej wersji piosenek legendarnych - przynajmniej dla mnie Polskich bard\u00f3w Kaczmarskiego, Gintrowskiego i\u00a0... "}, {"title": "Miko\u0142ajewski o Kaczmarskim: Konrad umar\u0142, Gustaw si\u0119 nie narodzi\u0142", "url": "https://wyborcza.pl/7,75517,2041953.html", "desc": " Apr 10, 2014  \u00b7  Miko\u0142ajewski o Kaczmarskim: Konrad umar\u0142, Gustaw si\u0119 nie narodzi\u0142 \u00b7 10 lat temu zmar\u0142 Jacek Kaczmarski. By\u0142 \"diabli, czy\u015b\u0107cowy i boski\" \u00b7 10\u00a0... "}], "co to": [{"title": "", "url": "/search?num=8", "desc": " Artist "}, {"title": "Ballada \u017cebracza www.kaczmarski.art.pl", "url": "https://www.kaczmarski.art.pl/tworczosc/wiersze/ballada-zebracza/", "desc": " Oct 10, 2017  \u00b7  Zapowied\u017a Jacka Kaczmarskiego do utworu spisana z albumu Bankiet. \u201eI na deser piosenka z przed dw\u00f3ch i p\u00f3l roku, ju\u017c z czas\u00f3w wolno\u015bci i\u00a0... "}, {"title": "Ballada \u017cebracza - tekst i akordy - Piosenka z tekstem", "url": "https://www.piosenkaztekstem.pl/opracowanie/jacek-kaczmarski-ballada-zebracza/", "desc": " Apr 5, 2012  \u00b7  Piosenk\u0119 t\u0119 Jacek Kaczmarski zapowiada, jako \"ju\u017c z czas\u00f3w wolno\u015bci i demokracji\", kt\u00f3ra nie zosta\u0142a puszczona w Radiu Wolna Europa. Odbudowa\u00a0... "}, {"title": "Jacek Kaczmarski - \"Ballada \u017cebracza\" - YouTube", "url": "https://www.youtube.com/watch?v=EODgeIigxlQ", "desc": " Sep 21, 2016  \u00b7  Dajcie mi, prosz\u0119, co \u0142aska. \u017bebrak \u2013 te\u017c cz\u0142owiek, do diaska! \u015apiewa\u0107 ju\u017c nie mam si\u0142y, \u017barty mi si\u0119 sko\u0144czy\u0142y. Siedz\u0119 na Placu Zamkowym Z\u00a0... "}, {"title": "Ballada \u017cebraczaka - o kim i dlaczego ocenzurowana?", "url": "https://kaczmarski.art.pl/forum/showthread.php?tid=7801&pid=194421", "desc": " Jan 17, 2012  \u00b7  Opr\u00f3cz Wojny postu ocenzurowany zosta\u0142 utw\u00f3r We Are the World oraz w\u0142a\u015bnie Ballada \u017cebracza. Pytanie \"dlaczego\" jest o tyle trudne, \u017ce nie\u00a0... "}, {"title": "Ballada \u017cebracza - Jacek Kaczmarski, Chwyty na gitar\u0119 - \u015apiewnik", "url": "https://spiewnik.wywrota.pl/jacek-kaczmarski/ballada-zebracza", "desc": " Rating   4.0  (3)   "}]}, "yt_search": [{"url": "https://www.youtube.com/watch?v=EODgeIigxlQ", "title": "Jacek Kaczmarski - \"Ballada \u017cebracza\" - YouTube"}, {"url": "https://www.youtube.com/watch?v=zXxJMbOkDTA", "title": "Jacek Kaczmarski - Ballada \u017cebracza | Tekst - YouTube"}, {"url": "https://www.youtube.com/watch?v=dm1ykMcE9gw", "title": "Jacek Kaczmarski - \"Jan Kochanowski\" - YouTube"}], "rating": "Big sad man talk. Man once strong, build big walls, pretty houses. Now man weak, no have strength. Man beg for food, other man say no. Other man say, go away, make city ugly. Sad man say he make city. He work hard, make tunnel, castle. Now man old, want rest, want eat. Poem make feel sad for man. Poem repeat much, sound like sad song. Poem good tell story, but sound too long song. It have big sad feel, 6/10.\n"}, "id": "69", "special": true}